soton_corenlppy/PostgresqlHandler.py
soton_corenlppy/SocialMediaParser.py
soton_corenlppy/SqlHandler.py
soton_corenlppy/__init__.py
soton_corenlppy/common_parse_lib.py
soton_corenlppy/config_helper.py
soton_corenlppy/time_helper.py
soton_corenlppy/lexico/__init__.py
soton_corenlppy/lexico/lexicon_bootstrapping_lib.py
soton_corenlppy/lexico/lexicon_lib.py
soton_corenlppy/lexico/wordnet_lib.py
soton_corenlppy/re/__init__.py
soton_corenlppy/re/comp_sem_lib.py
soton_corenlppy/re/dataset_support_lib.py
soton_corenlppy/re/logic_lib.py
soton_corenlppy/re/openie_lib.py
soton_corenlppy/re/sem_map_lib.py
soton_corenlppy/re/shallow_parse_lib.py
soton_corenlppy/sit_assess/__init__.py
soton_corenlppy/sit_assess/sit_assess_lib.py
soton_corenlppy-1.0.0.dist-info/LICENSE.txt
soton_corenlppy-1.0.0.dist-info/METADATA
soton_corenlppy-1.0.0.dist-info/WHEEL
soton_corenlppy-1.0.0.dist-info/top_level.txt
soton_corenlppy-1.0.0.dist-info/RECORD
