Metadata-Version: 2.1
Name: soton-corenlppy
Version: 1.0.0
Summary: NLP library providing support for information extraction applications
Home-page: https://www.ecs.soton.ac.uk/people/sem03
Author: University of Southampton
Author-email: sem03@soton.ac.uk
License: BSD
Keywords: nlp
Platform: UNKNOWN
Classifier: Development Status :: 6 - Mature
Classifier: Intended Audience :: Developers
Classifier: Topic :: Software Development :: Build Tools
Classifier: License :: OSI Approved :: BSD License
Classifier: Programming Language :: Python :: 3.7
Requires-Dist: nltk (>=3.4)
Requires-Dist: psycopg2 (>=2.8)
Requires-Dist: setuptools (>=46)
